setup.py
bkn_xi_dms/__init__.py
bkn_xi_dms/add_job_scan_detail.py
bkn_xi_dms/create_job_scan.py
bkn_xi_dms/document.py
bkn_xi_dms/employee_document.py
bkn_xi_dms/jenis_dokumen.py
bkn_xi_dms/scan.py
bkn_xi_dms/screening.py
bkn_xi_dms/search_employee.py
bkn_xi_dms/upload_detail.py
bkn_xi_dms.egg-info/PKG-INFO
bkn_xi_dms.egg-info/SOURCES.txt
bkn_xi_dms.egg-info/dependency_links.txt
bkn_xi_dms.egg-info/requires.txt
bkn_xi_dms.egg-info/top_level.txt
bkn_xi_dms/DAO/__init__.py
bkn_xi_dms/DAO/document_detail.py
bkn_xi_dms/auth/__init__.py
bkn_xi_dms/auth/login.py
bkn_xi_dms/auth/validation.py
bkn_xi_dms/report/__init__.py
bkn_xi_dms/report/prascan.py
bkn_xi_dms/report/r_logger.py
bkn_xi_dms/report/scan.py
bkn_xi_dms/request/__init__.py
bkn_xi_dms/request/request.py
bkn_xi_dms/utill/__init__.py
bkn_xi_dms/utill/installed_application.py
bkn_xi_dms/utill/rename_mapping.py
bkn_xi_dms/utill/rename_with_separator.py
bkn_xi_dms/utill/scan_mapping_file.py
bkn_xi_dms/utill/write_file.py