Metadata-Version: 2.1
Name: bkn-xi-dms
Version: 1.3
Summary: Document Management System (DMS) Assistan
Author: Rifo Pangemanan (ifodigital)
Author-email: <rifopangemanan@gmail.com>
Keywords: BKN
Classifier: Development Status :: 1 - Planning
Classifier: Intended Audience :: Developers
Classifier: Programming Language :: Python :: 3
Classifier: Operating System :: Unix
Classifier: Operating System :: MacOS :: MacOS X
Classifier: Operating System :: Microsoft :: Windows
